{"format_version":"1.16.0","minecraft:geometry":[{"description":{"identifier":"geometry.oreville_ans.kklrlzd","texture_width":1024,"texture_height":1024,"visible_bounds_width":2,"visible_bounds_height":1.5,"visible_bounds_offset":[0,0.25,0]},"bones":[{"name":"root","pivot":[0,0,0]},{"name":"bgzlujc","parent":"root","pivot":[0,0,0],"binding":"c.item_slot == 'torso' ? 'body' : q.item_slot_to_bone_name(c.item_slot)"},{"name":"llxmhpg","parent":"bgzlujc","pivot":[0,0,0],"cubes":[{"origin":[-3,0,2],"size":[6,8,3],"uv":{"north":{"uv":[171,695],"uv_size":[5.98,7.98]},"east":{"uv":[177,693],"uv_size":[2.98,7.98]},"south":{"uv":[171,695],"uv_size":[5.98,7.98]},"west":{"uv":[177,693],"uv_size":[2.98,7.98]},"up":{"uv":[182.98,703.98],"uv_size":[-5.98,-2.98]},"down":{"uv":[169.98,707.98],"uv_size":[-5.98,-2.98]}}}]},{"name":"znksytw","parent":"llxmhpg","pivot":[0,3,1.75],"cubes":[{"origin":[-1,2,-3],"size":[2,2,5],"pivot":[0,3,0],"rotation":[0,180,0],"uv":{"north":{"uv":[173,693],"uv_size":[1.98,1.98]},"east":{"uv":[169,693],"uv_size":[4.98,1.98]},"west":{"uv":[173.98,693],"uv_size":[-4.98,1.98]},"up":{"uv":[170.98,699.98],"uv_size":[-1.98,-4.98]},"down":{"uv":[170.98,704.98],"uv_size":[-1.98,-4.98]}}},{"origin":[-2.5,2,-7],"size":[5,2,5],"uv":{"north":{"uv":[164,704],"uv_size":[4.98,0.98]},"east":{"uv":[164,704],"uv_size":[4.98,0.98]},"south":{"uv":[164,704],"uv_size":[4.98,0.98]},"west":{"uv":[164,704],"uv_size":[4.98,0.98]},"up":{"uv":[168.98,697.98],"uv_size":[-4.98,-4.98]},"down":{"uv":[168.98,702.98],"uv_size":[-4.98,-4.98]}}}]}]}]}