{"format_version":"1.10.0","render_controllers":{"controller.render.oreville_ans.hcdyiyv":{"geometry":"Geometry.default","textures":["Texture.default"],"materials":[{"*":"Material.default"}]},"controller.render.oreville_ans.hcdyiyv.kohwqgs":{"geometry":"Geometry.tffgldx","textures":["Texture.hcdyiyv"],"materials":[{"*":"Material.default"},{"ntrstvk*":"Material.ntrstvk"},{"ntrstvk*":"Material.ntrstvk"}]},"controller.render.oreville_ans.hcdyiyv.eeyyvbj":{"geometry":"Geometry.ffvlxqy","textures":["Texture.gfsrdht"],"materials":[{"arueojm*":"Material.arueojm"},{"*":"Material.arueojm"}]},"controller.render.oreville_ans.hcdyiyv.xfasyyt":{"geometry":"Geometry.srmyzjz","textures":["Texture.zwucqag"],"materials":[{"ndkvsmg*":"Material.ndkvsmg"},{"*":"Material.ndkvsmg"}]}}}